LICENSE
MANIFEST.in
README.md
requirements.txt
setup.py
coincheck_api/__init__.py
coincheck_api/auth.py
coincheck_api/client.py
coincheck_api/exception.py
coincheck_api/settings.py
coincheck_api.egg-info/PKG-INFO
coincheck_api.egg-info/SOURCES.txt
coincheck_api.egg-info/dependency_links.txt
coincheck_api.egg-info/top_level.txt
coincheck_api/clients/__init__.py
coincheck_api/clients/account_api_client.py
coincheck_api/clients/api_client.py
coincheck_api/clients/borrow_api_client.py
coincheck_api/clients/order_api_client.py
coincheck_api/clients/private_api_client.py
coincheck_api/clients/public_api_client.py
coincheck_api/clients/transfer_api_client.py
coincheck_api/clients/withdraw_api_client.py