Metadata-Version: 1.0
Name: coincheck-api
Version: 0.8.1
Summary: A simple library to use CoinCheck API
Home-page: https://github.com/dakimura/coincheck_api
Author: dakimura
Author-email: dakimura@example.com
License: BSD 2-Clause License
